builder/__init__.py
builder/__main__.py
builder/cli/__init__.py
cmdinter/__init__.py
cmdinter-1.0.11.dist-info/DESCRIPTION.rst
cmdinter-1.0.11.dist-info/METADATA
cmdinter-1.0.11.dist-info/RECORD
cmdinter-1.0.11.dist-info/WHEEL
cmdinter-1.0.11.dist-info/entry_points.txt
cmdinter-1.0.11.dist-info/metadata.json
cmdinter-1.0.11.dist-info/top_level.txt
