Metadata-Version: 2.0
Name: cmdinter
Version: 1.0.11
Summary: A "command interface" for functions.
Home-page: https://github.com/feluxe/cmdinter
Author: Felix Meyer-Wolters
Author-email: felix@meyerwolters.de
License: unlicensed
Download-URL: https://github.com/feluxe/cmdinter/tarball/1.0.11
Keywords: command,interface,decorator
Platform: 
